Metadata-Version: 1.1
Name: jpgcoder
Version: 0.0.1
Summary: JPGCoder
Home-page: UNKNOWN
Author: Ilia Kalygin
Author-email: UNKNOWN
License: MIT
Keywords: jpgcoder
Platform: UNKNOWN
Classifier: Development Status :: 5 - Production/Stable
Classifier: Intended Audience :: Education
Classifier: Operating System :: Microsoft :: Windows :: Windows 10
Classifier: License :: OSI Approved :: MIT License
Classifier: Programming Language :: Python :: 3
